{
	"backtrace" : 0,
	"backtraceGraph" : 
	{
		"commands" : [],
		"files" : 
		[
			"CMakeLists.txt"
		],
		"nodes" : 
		[
			{
				"file" : 0
			}
		]
	},
	"dependencies" : 
	[
		{
			"backtrace" : 0,
			"id" : "apptimelineEditor_qmlimportscan::@6890427a1f51a3e7e1df"
		},
		{
			"backtrace" : 0,
			"id" : "apptimelineEditor_tooling::@6890427a1f51a3e7e1df"
		},
		{
			"id" : "ZERO_CHECK::@6890427a1f51a3e7e1df"
		}
	],
	"id" : "apptimelineEditor_autogen::@6890427a1f51a3e7e1df",
	"isGeneratorProvided" : true,
	"name" : "apptimelineEditor_autogen",
	"paths" : 
	{
		"build" : ".",
		"source" : "."
	},
	"sourceGroups" : 
	[
		{
			"name" : "",
			"sourceIndexes" : 
			[
				0
			]
		},
		{
			"name" : "CMake Rules",
			"sourceIndexes" : 
			[
				1,
				2
			]
		}
	],
	"sources" : 
	[
		{
			"backtrace" : 0,
			"isGenerated" : true,
			"path" : "cmake-build-debug-visual-studio-event-trace/CMakeFiles/apptimelineEditor_autogen",
			"sourceGroupIndex" : 0
		},
		{
			"backtrace" : 0,
			"isGenerated" : true,
			"path" : "cmake-build-debug-visual-studio-event-trace/CMakeFiles/66802e5876321b95924ddfbc5bb6d212/apptimelineEditor_autogen.rule",
			"sourceGroupIndex" : 1
		},
		{
			"backtrace" : 0,
			"isGenerated" : true,
			"path" : "cmake-build-debug-visual-studio-event-trace/CMakeFiles/c1f30403da10451a0b955884cca598e5/apptimelineEditor_qmlcache_loader.cpp.rule",
			"sourceGroupIndex" : 1
		}
	],
	"type" : "UTILITY"
}
